{
  "cards": [
    {
      "model": "basic",
      "front": "🚶 <b>andare</b>",
      "back": "Definition: to go<br>Present tense:<br><b>io vado</b><br>Example: Io vado a scuola = I go to school",
      "tags": [
        "a1",
        "verb",
        "presente"
      ]
    },
    {
      "model": "basic",
      "front": "🗣 <b>parlare</b>",
      "back": "Definition: to speak<br>Present tense:<br><b>io parlo</b><br>Example: Io parlo italiano = I speak Italian",
      "tags": [
        "a1",
        "verb",
        "presente"
      ]
    }
  ]
}